[{"id_usuario":null,"id_evento":"38532","id_tipo_evento":"1","ds_tipo_evento":"Corrida de Rua","id_resultado":"73692981","num_peito":"486","nome":"RODRIGO ALBANO","certificado":"https:\/\/adm.ativo.com\/certificado\/gerarcertificado\/id_evento\/38532\/num_peito\/486\/zwc\/007","nome_evento":"12\u00aa Meia & Maratona de Florian\u00f3polis - 42k de Floripa","evento_local":"Beira Mar Continental ","sexo":"M","modalidade":"10K","percurso":"10","categoria":"M3034","equipe":" ","ds_nome_equipe_revezamento":"","tempo_total":"00:41:37","tempo_bruto":"00:41:39","pace":"00:04:10","itens":{"classificacao_sexo":"11","classificacao_categoria":"2","classificacao_total":"11","velocidade_media":"1442"},"Classifica\u00e7\u00e3o Total":"11","mais_rapido_que":"99,34%"},{"id_usuario":null,"id_evento":"38532","id_tipo_evento":"1","ds_tipo_evento":"Corrida de Rua","id_resultado":"73692982","num_peito":"406","nome":"GUSTAVO MAITO","certificado":"https:\/\/adm.ativo.com\/certificado\/gerarcertificado\/id_evento\/38532\/num_peito\/406\/zwc\/007","nome_evento":"12\u00aa Meia & Maratona de Florian\u00f3polis - 42k de Floripa","evento_local":"Beira Mar Continental ","sexo":"M","modalidade":"10K","percurso":"10","categoria":"M2529","equipe":" ","ds_nome_equipe_revezamento":"","tempo_total":"00:41:38","tempo_bruto":"00:42:12","pace":"00:04:10","itens":{"classificacao_sexo":"12","classificacao_categoria":"4","classificacao_total":"12","velocidade_media":"1441"},"Classifica\u00e7\u00e3o Total":"12","mais_rapido_que":"99,29%"},{"id_usuario":null,"id_evento":"38532","id_tipo_evento":"1","ds_tipo_evento":"Corrida de Rua","id_resultado":"73692983","num_peito":"571","nome":"THAYANA SILVA DIAS","certificado":"https:\/\/adm.ativo.com\/certificado\/gerarcertificado\/id_evento\/38532\/num_peito\/571\/zwc\/007","nome_evento":"12\u00aa Meia & Maratona de Florian\u00f3polis - 42k de Floripa","evento_local":"Beira Mar Continental ","sexo":"F","modalidade":"10K","percurso":"10","categoria":"F2529","equipe":" ","ds_nome_equipe_revezamento":"","tempo_total":"00:41:45","tempo_bruto":"00:41:47","pace":"00:04:10","itens":{"classificacao_sexo":"1","classificacao_categoria":"1","classificacao_total":"13","velocidade_media":"1437"},"Classifica\u00e7\u00e3o Total":"13","mais_rapido_que":"99,23%"},{"id_usuario":null,"id_evento":"38532","id_tipo_evento":"1","ds_tipo_evento":"Corrida de Rua","id_resultado":"73692984","num_peito":"655","nome":"JOHN GEINER CASTILLO ARCOS","certificado":"https:\/\/adm.ativo.com\/certificado\/gerarcertificado\/id_evento\/38532\/num_peito\/655\/zwc\/007","nome_evento":"12\u00aa Meia & Maratona de Florian\u00f3polis - 42k de Floripa","evento_local":"Beira Mar Continental ","sexo":"M","modalidade":"10K","percurso":"10","categoria":"M3539","equipe":" ","ds_nome_equipe_revezamento":"","tempo_total":"00:42:14","tempo_bruto":"00:42:17","pace":"00:04:13","itens":{"classificacao_sexo":"13","classificacao_categoria":"1","classificacao_total":"14","velocidade_media":"1421"},"Classifica\u00e7\u00e3o Total":"14","mais_rapido_que":"99,17%"},{"id_usuario":null,"id_evento":"38532","id_tipo_evento":"1","ds_tipo_evento":"Corrida de Rua","id_resultado":"73692985","num_peito":"554","nome":"FELIPE DE TOLEDO MARINO","certificado":"https:\/\/adm.ativo.com\/certificado\/gerarcertificado\/id_evento\/38532\/num_peito\/554\/zwc\/007","nome_evento":"12\u00aa Meia & Maratona de Florian\u00f3polis - 42k de Floripa","evento_local":"Beira Mar Continental ","sexo":"M","modalidade":"10K","percurso":"10","categoria":"M4549","equipe":" ","ds_nome_equipe_revezamento":"","tempo_total":"00:42:21","tempo_bruto":"00:42:22","pace":"00:04:14","itens":{"classificacao_sexo":"14","classificacao_categoria":"3","classificacao_total":"15","velocidade_media":"1417"},"Classifica\u00e7\u00e3o Total":"15","mais_rapido_que":"99,11%"},{"id_usuario":null,"id_evento":"38532","id_tipo_evento":"1","ds_tipo_evento":"Corrida de Rua","id_resultado":"73692986","num_peito":"542","nome":"CHARLENE MORAIS DE OLIVEIRA CHAVES","certificado":"https:\/\/adm.ativo.com\/certificado\/gerarcertificado\/id_evento\/38532\/num_peito\/542\/zwc\/007","nome_evento":"12\u00aa Meia & Maratona de Florian\u00f3polis - 42k de Floripa","evento_local":"Beira Mar Continental ","sexo":"F","modalidade":"10K","percurso":"10","categoria":"F4044","equipe":" ","ds_nome_equipe_revezamento":"","tempo_total":"00:42:27","tempo_bruto":"00:42:29","pace":"00:04:15","itens":{"classificacao_sexo":"2","classificacao_categoria":"1","classificacao_total":"16","velocidade_media":"1413"},"Classifica\u00e7\u00e3o Total":"16","mais_rapido_que":"99,05%"},{"id_usuario":null,"id_evento":"38532","id_tipo_evento":"1","ds_tipo_evento":"Corrida de Rua","id_resultado":"73692987","num_peito":"573","nome":"WILLIAM DOUGLAS BONETTI DUTRA","certificado":"https:\/\/adm.ativo.com\/certificado\/gerarcertificado\/id_evento\/38532\/num_peito\/573\/zwc\/007","nome_evento":"12\u00aa Meia & Maratona de Florian\u00f3polis - 42k de Floripa","evento_local":"Beira Mar Continental ","sexo":"M","modalidade":"10K","percurso":"10","categoria":"M3034","equipe":" ","ds_nome_equipe_revezamento":"","tempo_total":"00:42:54","tempo_bruto":"00:42:56","pace":"00:04:17","itens":{"classificacao_sexo":"15","classificacao_categoria":"3","classificacao_total":"17","velocidade_media":"1399"},"Classifica\u00e7\u00e3o Total":"17","mais_rapido_que":"98,99%"},{"id_usuario":null,"id_evento":"38532","id_tipo_evento":"1","ds_tipo_evento":"Corrida de Rua","id_resultado":"73692988","num_peito":"489","nome":"FRANCIELI PEREIRA","certificado":"https:\/\/adm.ativo.com\/certificado\/gerarcertificado\/id_evento\/38532\/num_peito\/489\/zwc\/007","nome_evento":"12\u00aa Meia & Maratona de Florian\u00f3polis - 42k de Floripa","evento_local":"Beira Mar Continental ","sexo":"F","modalidade":"10K","percurso":"10","categoria":"F3034","equipe":" ","ds_nome_equipe_revezamento":"","tempo_total":"00:43:38","tempo_bruto":"00:43:41","pace":"00:04:22","itens":{"classificacao_sexo":"3","classificacao_categoria":"1","classificacao_total":"18","velocidade_media":"1375"},"Classifica\u00e7\u00e3o Total":"18","mais_rapido_que":"98,93%"},{"id_usuario":null,"id_evento":"38532","id_tipo_evento":"1","ds_tipo_evento":"Corrida de Rua","id_resultado":"73692989","num_peito":"353","nome":"GABRIELA PAULA SANTOS","certificado":"https:\/\/adm.ativo.com\/certificado\/gerarcertificado\/id_evento\/38532\/num_peito\/353\/zwc\/007","nome_evento":"12\u00aa Meia & Maratona de Florian\u00f3polis - 42k de Floripa","evento_local":"Beira Mar Continental ","sexo":"F","modalidade":"10K","percurso":"10","categoria":"F4549","equipe":" ","ds_nome_equipe_revezamento":"","tempo_total":"00:43:55","tempo_bruto":"00:43:57","pace":"00:04:24","itens":{"classificacao_sexo":"4","classificacao_categoria":"1","classificacao_total":"19","velocidade_media":"1366"},"Classifica\u00e7\u00e3o Total":"19","mais_rapido_que":"98,87%"},{"id_usuario":null,"id_evento":"38532","id_tipo_evento":"1","ds_tipo_evento":"Corrida de Rua","id_resultado":"73692990","num_peito":"354","nome":"GIOVANI GENOVESE","certificado":"https:\/\/adm.ativo.com\/certificado\/gerarcertificado\/id_evento\/38532\/num_peito\/354\/zwc\/007","nome_evento":"12\u00aa Meia & Maratona de Florian\u00f3polis - 42k de Floripa","evento_local":"Beira Mar Continental ","sexo":"M","modalidade":"10K","percurso":"10","categoria":"M4549","equipe":" ","ds_nome_equipe_revezamento":"","tempo_total":"00:43:59","tempo_bruto":"00:44:16","pace":"00:04:24","itens":{"classificacao_sexo":"16","classificacao_categoria":"4","classificacao_total":"20","velocidade_media":"1364"},"Classifica\u00e7\u00e3o Total":"20","mais_rapido_que":"98,81%"}]