[{"id_usuario":null,"id_evento":"38532","id_tipo_evento":"1","ds_tipo_evento":"Corrida de Rua","id_resultado":"73693531","num_peito":"638","nome":"ANNE LUISA NARDI","certificado":"https:\/\/adm.ativo.com\/certificado\/gerarcertificado\/id_evento\/38532\/num_peito\/638\/zwc\/007","nome_evento":"12\u00aa Meia & Maratona de Florian\u00f3polis - 42k de Floripa","evento_local":"Beira Mar Continental ","sexo":"F","modalidade":"10K","percurso":"10","categoria":"F4044","equipe":" ","ds_nome_equipe_revezamento":"","tempo_total":"01:24:20","tempo_bruto":"01:26:02","pace":"00:08:26","itens":{"classificacao_sexo":"276","classificacao_categoria":"55","classificacao_total":"547","velocidade_media":"711"},"Classifica\u00e7\u00e3o Total":"547","mais_rapido_que":"67,42%"},{"id_usuario":null,"id_evento":"38532","id_tipo_evento":"1","ds_tipo_evento":"Corrida de Rua","id_resultado":"73693532","num_peito":"543","nome":"MARIA EDUARDA CAMPOS BASTOS","certificado":"https:\/\/adm.ativo.com\/certificado\/gerarcertificado\/id_evento\/38532\/num_peito\/543\/zwc\/007","nome_evento":"12\u00aa Meia & Maratona de Florian\u00f3polis - 42k de Floripa","evento_local":"Beira Mar Continental ","sexo":"F","modalidade":"10K","percurso":"10","categoria":"F2024","equipe":" ","ds_nome_equipe_revezamento":"","tempo_total":"01:24:51","tempo_bruto":"01:25:13","pace":"00:08:29","itens":{"classificacao_sexo":"277","classificacao_categoria":"9","classificacao_total":"548","velocidade_media":"707"},"Classifica\u00e7\u00e3o Total":"548","mais_rapido_que":"67,36%"},{"id_usuario":null,"id_evento":"38532","id_tipo_evento":"1","ds_tipo_evento":"Corrida de Rua","id_resultado":"73693533","num_peito":"2359","nome":"M\u00c1RIO C\u00c9SAR FERREIRA","certificado":"https:\/\/adm.ativo.com\/certificado\/gerarcertificado\/id_evento\/38532\/num_peito\/2359\/zwc\/007","nome_evento":"12\u00aa Meia & Maratona de Florian\u00f3polis - 42k de Floripa","evento_local":"Beira Mar Continental ","sexo":"M","modalidade":"21K","percurso":"21","categoria":"M4549","equipe":" ","ds_nome_equipe_revezamento":"","tempo_total":"01:24:52","tempo_bruto":"01:24:53","pace":"00:04:02","itens":{"classificacao_sexo":"10","classificacao_categoria":"1","classificacao_total":"10","velocidade_media":"1485"},"Classifica\u00e7\u00e3o Total":"10","mais_rapido_que":"99,4%"},{"id_usuario":null,"id_evento":"38532","id_tipo_evento":"1","ds_tipo_evento":"Corrida de Rua","id_resultado":"73693534","num_peito":"55","nome":"AMANDA MAR\u00c7AL LEANDRO FERNANDES","certificado":"https:\/\/adm.ativo.com\/certificado\/gerarcertificado\/id_evento\/38532\/num_peito\/55\/zwc\/007","nome_evento":"12\u00aa Meia & Maratona de Florian\u00f3polis - 42k de Floripa","evento_local":"Beira Mar Continental ","sexo":"F","modalidade":"10K","percurso":"10","categoria":"F4549","equipe":" ","ds_nome_equipe_revezamento":"","tempo_total":"01:25:01","tempo_bruto":"01:25:23","pace":"00:08:30","itens":{"classificacao_sexo":"278","classificacao_categoria":"27","classificacao_total":"549","velocidade_media":"706"},"Classifica\u00e7\u00e3o Total":"549","mais_rapido_que":"67,3%"},{"id_usuario":null,"id_evento":"38532","id_tipo_evento":"1","ds_tipo_evento":"Corrida de Rua","id_resultado":"73693535","num_peito":"153","nome":"CAROLINA RAMO","certificado":"https:\/\/adm.ativo.com\/certificado\/gerarcertificado\/id_evento\/38532\/num_peito\/153\/zwc\/007","nome_evento":"12\u00aa Meia & Maratona de Florian\u00f3polis - 42k de Floripa","evento_local":"Beira Mar Continental ","sexo":"F","modalidade":"10K","percurso":"10","categoria":"F4044","equipe":" ","ds_nome_equipe_revezamento":"","tempo_total":"01:25:08","tempo_bruto":"01:25:22","pace":"00:08:31","itens":{"classificacao_sexo":"279","classificacao_categoria":"56","classificacao_total":"550","velocidade_media":"705"},"Classifica\u00e7\u00e3o Total":"550","mais_rapido_que":"67,24%"},{"id_usuario":null,"id_evento":"38532","id_tipo_evento":"1","ds_tipo_evento":"Corrida de Rua","id_resultado":"73693536","num_peito":"432","nome":"JOS\u00c9 DOMINGOS","certificado":"https:\/\/adm.ativo.com\/certificado\/gerarcertificado\/id_evento\/38532\/num_peito\/432\/zwc\/007","nome_evento":"12\u00aa Meia & Maratona de Florian\u00f3polis - 42k de Floripa","evento_local":"Beira Mar Continental ","sexo":"M","modalidade":"10K","percurso":"10","categoria":"M6569","equipe":" ","ds_nome_equipe_revezamento":"","tempo_total":"01:25:21","tempo_bruto":"01:28:39","pace":"00:08:32","itens":{"classificacao_sexo":"272","classificacao_categoria":"4","classificacao_total":"551","velocidade_media":"703"},"Classifica\u00e7\u00e3o Total":"551","mais_rapido_que":"67,18%"},{"id_usuario":null,"id_evento":"38532","id_tipo_evento":"1","ds_tipo_evento":"Corrida de Rua","id_resultado":"73693537","num_peito":"431","nome":"ISABEL CRISTINA DE SOUZA","certificado":"https:\/\/adm.ativo.com\/certificado\/gerarcertificado\/id_evento\/38532\/num_peito\/431\/zwc\/007","nome_evento":"12\u00aa Meia & Maratona de Florian\u00f3polis - 42k de Floripa","evento_local":"Beira Mar Continental ","sexo":"F","modalidade":"10K","percurso":"10","categoria":"F6569","equipe":" ","ds_nome_equipe_revezamento":"","tempo_total":"01:25:24","tempo_bruto":"01:28:39","pace":"00:08:32","itens":{"classificacao_sexo":"280","classificacao_categoria":"1","classificacao_total":"552","velocidade_media":"703"},"Classifica\u00e7\u00e3o Total":"552","mais_rapido_que":"67,12%"},{"id_usuario":null,"id_evento":"38532","id_tipo_evento":"1","ds_tipo_evento":"Corrida de Rua","id_resultado":"73693538","num_peito":"506","nome":"ISABEL NEVES MACIEL","certificado":"https:\/\/adm.ativo.com\/certificado\/gerarcertificado\/id_evento\/38532\/num_peito\/506\/zwc\/007","nome_evento":"12\u00aa Meia & Maratona de Florian\u00f3polis - 42k de Floripa","evento_local":"Beira Mar Continental ","sexo":"F","modalidade":"10K","percurso":"10","categoria":"F5054","equipe":" ","ds_nome_equipe_revezamento":"","tempo_total":"01:25:30","tempo_bruto":"01:26:09","pace":"00:08:33","itens":{"classificacao_sexo":"281","classificacao_categoria":"17","classificacao_total":"553","velocidade_media":"702"},"Classifica\u00e7\u00e3o Total":"553","mais_rapido_que":"67,06%"},{"id_usuario":null,"id_evento":"38532","id_tipo_evento":"1","ds_tipo_evento":"Corrida de Rua","id_resultado":"73693539","num_peito":"173","nome":"ONDINA RIBEIRO SILVA SOUZA","certificado":"https:\/\/adm.ativo.com\/certificado\/gerarcertificado\/id_evento\/38532\/num_peito\/173\/zwc\/007","nome_evento":"12\u00aa Meia & Maratona de Florian\u00f3polis - 42k de Floripa","evento_local":"Beira Mar Continental ","sexo":"F","modalidade":"10K","percurso":"10","categoria":"F6064","equipe":" ","ds_nome_equipe_revezamento":"","tempo_total":"01:25:34","tempo_bruto":"01:25:45","pace":"00:08:33","itens":{"classificacao_sexo":"282","classificacao_categoria":"8","classificacao_total":"554","velocidade_media":"701"},"Classifica\u00e7\u00e3o Total":"554","mais_rapido_que":"67%"},{"id_usuario":null,"id_evento":"38532","id_tipo_evento":"1","ds_tipo_evento":"Corrida de Rua","id_resultado":"73693540","num_peito":"78","nome":"KELI SOARES DE ANHAIA","certificado":"https:\/\/adm.ativo.com\/certificado\/gerarcertificado\/id_evento\/38532\/num_peito\/78\/zwc\/007","nome_evento":"12\u00aa Meia & Maratona de Florian\u00f3polis - 42k de Floripa","evento_local":"Beira Mar Continental ","sexo":"F","modalidade":"10K","percurso":"10","categoria":"F4044","equipe":" ","ds_nome_equipe_revezamento":"","tempo_total":"01:25:38","tempo_bruto":"01:25:52","pace":"00:08:34","itens":{"classificacao_sexo":"283","classificacao_categoria":"57","classificacao_total":"555","velocidade_media":"701"},"Classifica\u00e7\u00e3o Total":"555","mais_rapido_que":"66,94%"}]